MILWRM/MILWRM.py
MILWRM/MxIF.py
MILWRM/ST.py
MILWRM/__init__.py
MILWRM/_version.py
MILWRM-1.1.1.dist-info/LICENSE
MILWRM-1.1.1.dist-info/METADATA
MILWRM-1.1.1.dist-info/WHEEL
MILWRM-1.1.1.dist-info/top_level.txt
MILWRM-1.1.1.dist-info/RECORD
