Metadata-Version: 2.1
Name: MILWRM
Version: 1.1.1
Summary: Multiplex Image Labeling With Regional Morphology
Home-page: https://github.com/codyheiser/MILWRM
Author: Cody Heiser
Author-email: cody.n.heiser@vanderbilt.edu
License: UNKNOWN
Platform: UNKNOWN
Classifier: Programming Language :: Python :: 3
Classifier: Operating System :: OS Independent
Classifier: Intended Audience :: Developers
Classifier: Intended Audience :: Science/Research
Classifier: License :: OSI Approved :: MIT License
Classifier: Topic :: Scientific/Engineering
Requires-Python: >=3.6
Requires-Dist: imagecodecs
Requires-Dist: matplotlib
Requires-Dist: numpy
Requires-Dist: pandas
Requires-Dist: scanpy
Requires-Dist: scikit-image
Requires-Dist: scikit-learn
Requires-Dist: scipy
Requires-Dist: seaborn
Requires-Dist: squidpy
